Workbook

Sheet Содержание
A1: Лабораторная работа №6
A3: Раздел | B3: Содержание
A4: Задание 1 | B4: Кругозор / Горизонт / Общий отчет; расчеты, доли, диаграммы
A5: Задание 2 | B5: Калькуляция стоимости салата
A6: Задание 3 | B6: Абоненты: льготы, долги, анализ по фамилиям и месяцам
A7: Задание 4 | B7: Прокат: просрочка, пеня, дни проката, оплата
A8: Задание 5 | B8: Детские пособия: возраст, выплаты, анализ
A9: Задание 6 | B9: Стаж, надбавки, оплата труда
A10: Задание 7 | B10: Больничные: стаж, оплата, анализ
A11: Задание 8 | B11: Сотрудники: возраст, стаж, надбавки, зарплата
A12: Задание 9 | B12: Больничный лист: стаж, дни, оплата, анализ
A13: Задание 10 | B13: Графики SIN, COS, параболы и кусочной функции

Sheet Задание 1
A1: Задание 1. Объем продаж книг магазином «Кругозор» | I1: Выборочное суммирование
A2: 1 квартал | I2: Техническая + юридическая: январь и февраль | J2: =SUM(B5:C5,B8:C8) -> 3351
I3: Детская + художественная: февраль и март | J3: =SUM(C6:D6,C7:D7) -> 2029.23
A4: Категория литературы | B4: Январь | C4: Февраль | D4: Март | E4: Итого | F4: МАКС | G4: МИН
A5: Техническая | B5: 1234 | C5: 345 | D5: 234 | E5: =SUM(B5:D5) -> 1813 | F5: =MAX(B5:D5) -> 1234 | G5: =MIN(B5:D5) -> 234
A6: Художественная | B6: 654 | C6: 765 | D6: 265 | E6: =SUM(B6:D6) -> 1684 | F6: =MAX(B6:D6) -> 765 | G6: =MIN(B6:D6) -> 265
A7: Детская | B7: 5432 | C7: 555.23 | D7: 444 | E7: =SUM(B7:D7) -> 6431.23 | F7: =MAX(B7:D7) -> 5432 | G7: =MIN(B7:D7) -> 444
A8: Юридическая | B8: 987 | C8: 785 | D8: 657 | E8: =SUM(B8:D8) -> 2429 | F8: =MAX(B8:D8) -> 987 | G8: =MIN(B8:D8) -> 657
A9: Экономическая | B9: 456.77 | C9: 123.45 | D9: 5454.67 | E9: =SUM(B9:D9) -> 6034.89 | F9: =MAX(B9:D9) -> 5454.67 | G9: =MIN(B9:D9) -> 123.45
A11: Итого | B11: =SUM(B5:B9) -> 8763.77 | C11: =SUM(C5:C9) -> 2573.68 | D11: =SUM(D5:D9) -> 7054.67 | E11: =SUM(E5:E9) -> 18392.12
A14: Доли по каждой категории: месяц / итог категории
A15: Категория | B15: Январь | C15: Февраль | D15: Март | E15: Итого
A16: =A5 -> Техническая | B16: =B5/$E5 -> 0.68063982 | C16: =C5/$E5 -> 0.19029233 | D16: =D5/$E5 -> 0.12906784 | E16: =SUM(B16:D16) -> 1
A17: =A6 -> Художественная | B17: =B6/$E6 -> 0.38836105 | C17: =C6/$E6 -> 0.45427553 | D17: =D6/$E6 -> 0.15736342 | E17: =SUM(B17:D17) -> 1
A18: =A7 -> Детская | B18: =B7/$E7 -> 0.84462848 | C18: =C7/$E7 -> 0.086333407 | D18: =D7/$E7 -> 0.069038116 | E18: =SUM(B18:D18) -> 1
A19: =A8 -> Юридическая | B19: =B8/$E8 -> 0.40634006 | C19: =C8/$E8 -> 0.32317826 | D19: =D8/$E8 -> 0.27048168 | E19: =SUM(B19:D19) -> 1
A20: =A9 -> Экономическая | B20: =B9/$E9 -> 0.075688206 | C20: =C9/$E9 -> 0.020456048 | D20: =D9/$E9 -> 0.90385575 | E20: =SUM(B20:D20) -> 1
A22: Доли каждого значения от общей стоимости всей литературы
A23: Категория | B23: Январь | C23: Февраль | D23: Март | E23: Итого
A24: =A5 -> Техническая | B24: =B5/$E$11 -> 0.067093951 | C24: =C5/$E$11 -> 0.018758033 | D24: =D5/$E$11 -> 0.01272284 | E24: =E5/$E$11 -> 0.098574824
A25: =A6 -> Художественная | B25: =B6/$E$11 -> 0.035558707 | C25: =C6/$E$11 -> 0.0415939 | D25: =D6/$E$11 -> 0.014408344 | E25: =E6/$E$11 -> 0.091560951
A26: =A7 -> Детская | B26: =B7/$E$11 -> 0.29534388 | C26: =C7/$E$11 -> 0.030188472 | D26: =D7/$E$11 -> 0.024140773 | E26: =E7/$E$11 -> 0.34967312
A27: =A8 -> Юридическая | B27: =B8/$E$11 -> 0.053664287 | C27: =C8/$E$11 -> 0.042681322 | D27: =D8/$E$11 -> 0.03572182 | E27: =E8/$E$11 -> 0.13206743
A28: =A9 -> Экономическая | B28: =B9/$E$11 -> 0.024835092 | C28: =C9/$E$11 -> 0.0067121137 | D28: =D9/$E$11 -> 0.29657647 | E28: =E9/$E$11 -> 0.32812367
A30: Структура с пустой строкой для расширения: вставка новых категорий/месяцев не требует ручного переписывания итоговой формулы
A31: Категория | B31: Январь | C31: Февраль | D31: Март | E31: Новый месяц | F31: Итого
A32: =A5 -> Техническая | B32: =B5 -> 1234 | C32: =C5 -> 345 | D32: =D5 -> 234 | E32: 0 | F32: =SUM(B32:E32) -> 1813
A33: =A6 -> Художественная | B33: =B6 -> 654 | C33: =C6 -> 765 | D33: =D6 -> 265 | E33: 0 | F33: =SUM(B33:E33) -> 1684
A34: =A7 -> Детская | B34: =B7 -> 5432 | C34: =C7 -> 555.23 | D34: =D7 -> 444 | E34: 0 | F34: =SUM(B34:E34) -> 6431.23
A35: =A8 -> Юридическая | B35: =B8 -> 987 | C35: =C8 -> 785 | D35: =D8 -> 657 | E35: 0 | F35: =SUM(B35:E35) -> 2429
A36: =A9 -> Экономическая | B36: =B9 -> 456.77 | C36: =C9 -> 123.45 | D36: =D9 -> 5454.67 | E36: 0 | F36: =SUM(B36:E36) -> 6034.89
A38: Итого | B38: =SUM(B32:B37) -> 8763.77 | C38: =SUM(C32:C37) -> 2573.68 | D38: =SUM(D32:D37) -> 7054.67 | E38: =SUM(E32:E37) -> 0 | F38: =SUM(F32:F37) -> 18392.12

Sheet Горизонт
A1: Магазин «Горизонт» - объем продаж
A4: Категория литературы | B4: Январь | C4: Февраль | D4: Март | E4: Итого
A5: Техническая | B5: 1500 | C5: 420 | D5: 300 | E5: =SUM(B5:D5) -> 2220
A6: Художественная | B6: 800 | C6: 710 | D6: 310 | E6: =SUM(B6:D6) -> 1820
A7: Детская | B7: 5000 | C7: 620 | D7: 500 | E7: =SUM(B7:D7) -> 6120
A8: Юридическая | B8: 1100 | C8: 800 | D8: 700 | E8: =SUM(B8:D8) -> 2600
A9: Экономическая | B9: 700 | C9: 250 | D9: 5200 | E9: =SUM(B9:D9) -> 6150
A11: Итого | B11: =SUM(B5:B9) -> 9100 | C11: =SUM(C5:C9) -> 2800 | D11: =SUM(D5:D9) -> 7010 | E11: =SUM(E5:E9) -> 18910

Sheet Общий отчет
A1: Общий отчет - два магазина
A4: Категория литературы | B4: Январь | C4: Февраль | D4: Март | E4: Итого
A5: ='Задание 1'!A5 -> Техническая | B5: ='Задание 1'!B5+Горизонт!B5 -> 2734 | C5: ='Задание 1'!C5+Горизонт!C5 -> 765 | D5: ='Задание 1'!D5+Горизонт!D5 -> 534 | E5: =SUM(B5:D5) -> 4033
A6: ='Задание 1'!A6 -> Художественная | B6: ='Задание 1'!B6+Горизонт!B6 -> 1454 | C6: ='Задание 1'!C6+Горизонт!C6 -> 1475 | D6: ='Задание 1'!D6+Горизонт!D6 -> 575 | E6: =SUM(B6:D6) -> 3504
A7: ='Задание 1'!A7 -> Детская | B7: ='Задание 1'!B7+Горизонт!B7 -> 10432 | C7: ='Задание 1'!C7+Горизонт!C7 -> 1175.23 | D7: ='Задание 1'!D7+Горизонт!D7 -> 944 | E7: =SUM(B7:D7) -> 12551.23
A8: ='Задание 1'!A8 -> Юридическая | B8: ='Задание 1'!B8+Горизонт!B8 -> 2087 | C8: ='Задание 1'!C8+Горизонт!C8 -> 1585 | D8: ='Задание 1'!D8+Горизонт!D8 -> 1357 | E8: =SUM(B8:D8) -> 5029
A9: ='Задание 1'!A9 -> Экономическая | B9: ='Задание 1'!B9+Горизонт!B9 -> 1156.77 | C9: ='Задание 1'!C9+Горизонт!C9 -> 373.45 | D9: ='Задание 1'!D9+Горизонт!D9 -> 10654.67 | E9: =SUM(B9:D9) -> 12184.89
A11: Итого | B11: =SUM(B5:B9) -> 17863.77 | C11: =SUM(C5:C9) -> 5373.68 | D11: =SUM(D5:D9) -> 14064.67 | E11: =SUM(E5:E9) -> 37302.12

Sheet Задание 2
A1: Задание 2. Расчет стоимости продуктов для приготовления салата
A4: № | B4: Наименование | C4: Ед. изм. | D4: Цена | E4: Кол-во | F4: Вес, г | G4: Стоимость | H4: Состав в %
A5: 1 | B5: Картофель | C5: кг | D5: 5 | E5: 0.3 | F5: 300 | G5: =D5*E5 -> 1.5 | H5: =G5/$G$11 -> 0.033296337
A6: 2 | B6: Фасоль | C6: кг | D6: 12 | E6: 0.25 | F6: 250 | G6: =D6*E6 -> 3 | H6: =G6/$G$11 -> 0.066592675
A7: 3 | B7: Помидоры | C7: кг | D7: 30 | E7: 0.55 | F7: 550 | G7: =D7*E7 -> 16.5 | H7: =G7/$G$11 -> 0.36625971
A8: 4 | B8: Рыба | C8: банка | D8: 14.5 | E8: 1 | F8: 600 | G8: =D8*E8 -> 14.5 | H8: =G8/$G$11 -> 0.32186459
A9: 5 | B9: Капуста | C9: кг | D9: 9 | E9: 0.75 | F9: 750 | G9: =D9*E9 -> 6.75 | H9: =G9/$G$11 -> 0.14983352
A10: 6 | B10: Яйца | C10: шт | D10: 1.4 | E10: 2 | F10: 40 | G10: =D10*E10 -> 2.8 | H10: =G10/$G$11 -> 0.062153163
B11: ИТОГО: | E11: =SUM(E5:E10) -> 4.85 | F11: =SUM(F5:F10) -> 2490 | G11: =SUM(G5:G10) -> 45.05 | H11: =SUM(H5:H10) -> 1
B13: Вес одной порции, г | C13: 100
B14: Количество порций | C14: =F11/C13 -> 24.9
B15: Стоимость продуктов одной порции | C15: =G11/C14 -> 1.8092369
B16: Зарплата сотрудников | C16: 0.25 | D16: =C15*C16 -> 0.45230924
B17: Накладные расходы | C17: 0.8 | D17: =C15*C17 -> 1.4473896
B18: Стоимость порции для покупателя | C18: =C15+D16+D17 -> 3.7089357

Sheet Задание 3
A1: Задание 3. Абоненты: льготы, оплата и долги
I2: Тариф без льгот | J2: 1000
A4: № | B4: Месяц | C4: ФИО | D4: Номер телефона | E4: Льгота | F4: Оплата | G4: Внесено | H4: Долг
A5: 1 | B5: Январь | C5: Иванов И.И. | D5: 8170100000 | E5: 0 | F5: =IF(E5=0,$J$2,IF(E5=1,$J$2*75%,$J$2*50%)) -> 1000 | G5: 700 | H5: =MAX(F5-G5,0) -> 300
A6: 2 | B6: Январь | C6: Петров П.П. | D6: 8170100001 | E6: 1 | F6: =IF(E6=0,$J$2,IF(E6=1,$J$2*75%,$J$2*50%)) -> 750 | G6: 900 | H6: =MAX(F6-G6,0) -> 0
A7: 3 | B7: Январь | C7: Сидорова А.А. | D7: 8170100002 | E7: 2 | F7: =IF(E7=0,$J$2,IF(E7=1,$J$2*75%,$J$2*50%)) -> 500 | G7: 850 | H7: =MAX(F7-G7,0) -> 0
A8: 4 | B8: Январь | C8: Кузнецов К.К. | D8: 8170100003 | E8: 0 | F8: =IF(E8=0,$J$2,IF(E8=1,$J$2*75%,$J$2*50%)) -> 1000 | G8: 650 | H8: =MAX(F8-G8,0) -> 350
A9: 5 | B9: Февраль | C9: Иванов И.И. | D9: 8170100004 | E9: 1 | F9: =IF(E9=0,$J$2,IF(E9=1,$J$2*75%,$J$2*50%)) -> 750 | G9: 1000 | H9: =MAX(F9-G9,0) -> 0
A10: 6 | B10: Февраль | C10: Петров П.П. | D10: 8170100005 | E10: 0 | F10: =IF(E10=0,$J$2,IF(E10=1,$J$2*75%,$J$2*50%)) -> 1000 | G10: 800 | H10: =MAX(F10-G10,0) -> 200
A11: 7 | B11: Февраль | C11: Сидорова А.А. | D11: 8170100006 | E11: 2 | F11: =IF(E11=0,$J$2,IF(E11=1,$J$2*75%,$J$2*50%)) -> 500 | G11: 750 | H11: =MAX(F11-G11,0) -> 0
A12: 8 | B12: Февраль | C12: Кузнецов К.К. | D12: 8170100007 | E12: 1 | F12: =IF(E12=0,$J$2,IF(E12=1,$J$2*75%,$J$2*50%)) -> 750 | G12: 1100 | H12: =MAX(F12-G12,0) -> 0
A13: 9 | B13: Март | C13: Иванов И.И. | D13: 8170100008 | E13: 0 | F13: =IF(E13=0,$J$2,IF(E13=1,$J$2*75%,$J$2*50%)) -> 1000 | G13: 600 | H13: =MAX(F13-G13,0) -> 400
A14: 10 | B14: Март | C14: Петров П.П. | D14: 8170100009 | E14: 2 | F14: =IF(E14=0,$J$2,IF(E14=1,$J$2*75%,$J$2*50%)) -> 500 | G14: 950 | H14: =MAX(F14-G14,0) -> 0
A15: 11 | B15: Март | C15: Сидорова А.А. | D15: 8170100010 | E15: 1 | F15: =IF(E15=0,$J$2,IF(E15=1,$J$2*75%,$J$2*50%)) -> 750 | G15: 900 | H15: =MAX(F15-G15,0) -> 0
A16: 12 | B16: Март | C16: Кузнецов К.К. | D16: 8170100011 | E16: 0 | F16: =IF(E16=0,$J$2,IF(E16=1,$J$2*75%,$J$2*50%)) -> 1000 | G16: 700 | H16: =MAX(F16-G16,0) -> 300
I19: Общая сумма внесенной оплаты | J19: =SUM(G5:G16) -> 9900
I20: Общая сумма долга | J20: =SUM(H5:H16) -> 1550
I21: Средний долг | J21: =AVERAGE(H5:H16) -> 129.16667
I22: Количество абонентов с долгом больше среднего | J22: =COUNTIF(H5:H16,">"&J21) -> 5
I23: Минимальный долг | J23: =MIN(H5:H16) -> 0
I24: Максимальный долг | J24: =MAX(H5:H16) -> 400
I27: Долг по фамилиям
I28: ФИО | J28: Долг
I29: Иванов И.И. | J29: =SUMIF(C5:C16,I29,H5:H16) -> 700
I30: Петров П.П. | J30: =SUMIF(C5:C16,I30,H5:H16) -> 200
I31: Сидорова А.А. | J31: =SUMIF(C5:C16,I31,H5:H16) -> 0
I32: Кузнецов К.К. | J32: =SUMIF(C5:C16,I32,H5:H16) -> 650
I34: Оплата по месяцам
I35: Месяц | J35: Оплата | K35: Внесено
I36: Январь | J36: =SUMIF(B5:B16,I36,F5:F16) -> 3250 | K36: =SUMIF(B5:B16,I36,G5:G16) -> 3100
I37: Февраль | J37: =SUMIF(B5:B16,I37,F5:F16) -> 3000 | K37: =SUMIF(B5:B16,I37,G5:G16) -> 3650
I38: Март | J38: =SUMIF(B5:B16,I38,F5:F16) -> 3250 | K38: =SUMIF(B5:B16,I38,G5:G16) -> 3150

Sheet Задание 4
A1: Задание 4. Прокат: просрочка, пеня и сумма к оплате
A4: № | B4: Наименование | C4: Стоимость проката в сутки | D4: Дата выдачи | E4: Дата сдачи | F4: Просрочено дней | G4: Пеня | H4: Дней в прокате | I4: К оплате | K4: Анализ
A5: 1 | B5: Фильм | C5: 120 | D5: 46276 | E5: 46299 | F5: =MAX(TODAY()-E5,0) -> 3 | G5: =C5*IF(F5<5,F5*0.0005,IF(F5<=10,5*0.0005+(F5-5)*0.001,5*0.0005+5*0.001+(F5-10)*0.003)) -> 0.18 | H5: =E5-D5 -> 23 | I5: =C5*H5+G5 -> 2760.18 | K5: Количество просроченных заказов | L5: =COUNTIF(F5:F14,">0") -> 10
A6: 2 | B6: Игра | C6: 80 | D6: 46273 | E6: 46295 | F6: =MAX(TODAY()-E6,0) -> 7 | G6: =C6*IF(F6<5,F6*0.0005,IF(F6<=10,5*0.0005+(F6-5)*0.001,5*0.0005+5*0.001+(F6-10)*0.003)) -> 0.36 | H6: =E6-D6 -> 22 | I6: =C6*H6+G6 -> 1760.36 | K6: Минимум дней в прокате | L6: =MIN(H5:H14) -> 19
A7: 3 | B7: Книга | C7: 50 | D7: 46270 | E7: 46290 | F7: =MAX(TODAY()-E7,0) -> 12 | G7: =C7*IF(F7<5,F7*0.0005,IF(F7<=10,5*0.0005+(F7-5)*0.001,5*0.0005+5*0.001+(F7-10)*0.003)) -> 0.675 | H7: =E7-D7 -> 20 | I7: =C7*H7+G7 -> 1000.675 | K7: Максимум дней в прокате | L7: =MAX(H5:H14) -> 45
A8: 4 | B8: Журнал | C8: 30 | D8: 46267 | E8: 46286 | F8: =MAX(TODAY()-E8,0) -> 16 | G8: =C8*IF(F8<5,F8*0.0005,IF(F8<=10,5*0.0005+(F8-5)*0.001,5*0.0005+5*0.001+(F8-10)*0.003)) -> 0.765 | H8: =E8-D8 -> 19 | I8: =C8*H8+G8 -> 570.765
A9: 5 | B9: Фильм | C9: 120 | D9: 46264 | E9: 46301 | F9: =MAX(TODAY()-E9,0) -> 1 | G9: =C9*IF(F9<5,F9*0.0005,IF(F9<=10,5*0.0005+(F9-5)*0.001,5*0.0005+5*0.001+(F9-10)*0.003)) -> 0.06 | H9: =E9-D9 -> 37 | I9: =C9*H9+G9 -> 4440.06 | K9: Наименование | L9: К оплате
A10: 6 | B10: Игра | C10: 80 | D10: 46261 | E10: 46293 | F10: =MAX(TODAY()-E10,0) -> 9 | G10: =C10*IF(F10<5,F10*0.0005,IF(F10<=10,5*0.0005+(F10-5)*0.001,5*0.0005+5*0.001+(F10-10)*0.003)) -> 0.52 | H10: =E10-D10 -> 32 | I10: =C10*H10+G10 -> 2560.52 | K10: Фильм | L10: =SUMIF(B5:B14,K10,I5:I14) -> 10685.1
A11: 7 | B11: Книга | C11: 50 | D11: 46258 | E11: 46289 | F11: =MAX(TODAY()-E11,0) -> 13 | G11: =C11*IF(F11<5,F11*0.0005,IF(F11<=10,5*0.0005+(F11-5)*0.001,5*0.0005+5*0.001+(F11-10)*0.003)) -> 0.825 | H11: =E11-D11 -> 31 | I11: =C11*H11+G11 -> 1550.825 | K11: Игра | L11: =SUMIF(B5:B14,K11,I5:I14) -> 7921.32
A12: 8 | B12: Журнал | C12: 30 | D12: 46255 | E12: 46297 | F12: =MAX(TODAY()-E12,0) -> 5 | G12: =C12*IF(F12<5,F12*0.0005,IF(F12<=10,5*0.0005+(F12-5)*0.001,5*0.0005+5*0.001+(F12-10)*0.003)) -> 0.075 | H12: =E12-D12 -> 42 | I12: =C12*H12+G12 -> 1260.075 | K12: Книга | L12: =SUMIF(B5:B14,K12,I5:I14) -> 2551.5
A13: 9 | B13: Фильм | C13: 120 | D13: 46252 | E13: 46281 | F13: =MAX(TODAY()-E13,0) -> 21 | G13: =C13*IF(F13<5,F13*0.0005,IF(F13<=10,5*0.0005+(F13-5)*0.001,5*0.0005+5*0.001+(F13-10)*0.003)) -> 4.86 | H13: =E13-D13 -> 29 | I13: =C13*H13+G13 -> 3484.86 | K13: Журнал | L13: =SUMIF(B5:B14,K13,I5:I14) -> 1830.84
A14: 10 | B14: Игра | C14: 80 | D14: 46249 | E14: 46294 | F14: =MAX(TODAY()-E14,0) -> 8 | G14: =C14*IF(F14<5,F14*0.0005,IF(F14<=10,5*0.0005+(F14-5)*0.001,5*0.0005+5*0.001+(F14-10)*0.003)) -> 0.44 | H14: =E14-D14 -> 45 | I14: =C14*H14+G14 -> 3600.44

Sheet Задание 5
A1: Задание 5. Детские пособия
I2: Минимальный заработок | J2: 20000
A4: № | B4: ФИО | C4: Дата рождения | D4: Месяц выплаты пособия | E4: Возраст | F4: Сумма пособия
A5: 1 | B5: Иванов | C5: 45667 | D5: Январь | E5: =DATEDIF(C5,TODAY(),"Y") -> 1 | F5: =IF(E5<3,$J$2,IF(E5<8,$J$2*80%,IF(E5<=17,$J$2*60%,0))) -> 20000 | I5: Общая сумма пособий | J5: =SUM(F5:F14) -> 128000
A6: 2 | B6: Петров | C6: 44321 | D6: Февраль | E6: =DATEDIF(C6,TODAY(),"Y") -> 5 | F6: =IF(E6<3,$J$2,IF(E6<8,$J$2*80%,IF(E6<=17,$J$2*60%,0))) -> 16000 | I6: Средний возраст | J6: =AVERAGE(E5:E14) -> 9.5
A7: 3 | B7: Сидорова | C7: 43355 | D7: Март | E7: =DATEDIF(C7,TODAY(),"Y") -> 8 | F7: =IF(E7<3,$J$2,IF(E7<8,$J$2*80%,IF(E7<=17,$J$2*60%,0))) -> 12000 | I7: Количество детей старше 8 лет | J7: =COUNTIF(E5:E14,">8") -> 4
A8: 4 | B8: Кузнецов | C8: 40240 | D8: Январь | E8: =DATEDIF(C8,TODAY(),"Y") -> 16 | F8: =IF(E8<3,$J$2,IF(E8<8,$J$2*80%,IF(E8<=17,$J$2*60%,0))) -> 12000
A9: 5 | B9: Иванов | C9: 38540 | D9: Февраль | E9: =DATEDIF(C9,TODAY(),"Y") -> 21 | F9: =IF(E9<3,$J$2,IF(E9<8,$J$2*80%,IF(E9<=17,$J$2*60%,0))) -> 0 | I9: ФИО | J9: Сумма пособия
A10: 6 | B10: Петров | C10: 45336 | D10: Март | E10: =DATEDIF(C10,TODAY(),"Y") -> 2 | F10: =IF(E10<3,$J$2,IF(E10<8,$J$2*80%,IF(E10<=17,$J$2*60%,0))) -> 20000 | I10: Иванов | J10: =SUMIF(B5:B14,I10,F5:F14) -> 20000
A11: 7 | B11: Сидорова | C11: 43789 | D11: Январь | E11: =DATEDIF(C11,TODAY(),"Y") -> 6 | F11: =IF(E11<3,$J$2,IF(E11<8,$J$2*80%,IF(E11<=17,$J$2*60%,0))) -> 16000 | I11: Петров | J11: =SUMIF(B5:B14,I11,F5:F14) -> 56000
A12: 8 | B12: Кузнецов | C12: 40700 | D12: Февраль | E12: =DATEDIF(C12,TODAY(),"Y") -> 15 | F12: =IF(E12<3,$J$2,IF(E12<8,$J$2*80%,IF(E12<=17,$J$2*60%,0))) -> 12000 | I12: Сидорова | J12: =SUMIF(B5:B14,I12,F5:F14) -> 28000
A13: 9 | B13: Иванов | C13: 39302 | D13: Март | E13: =DATEDIF(C13,TODAY(),"Y") -> 19 | F13: =IF(E13<3,$J$2,IF(E13<8,$J$2*80%,IF(E13<=17,$J$2*60%,0))) -> 0 | I13: Кузнецов | J13: =SUMIF(B5:B14,I13,F5:F14) -> 24000
A14: 10 | B14: Петров | C14: 45261 | D14: Январь | E14: =DATEDIF(C14,TODAY(),"Y") -> 2 | F14: =IF(E14<3,$J$2,IF(E14<8,$J$2*80%,IF(E14<=17,$J$2*60%,0))) -> 20000
I15: Месяц | J15: Сумма пособия
I16: Январь | J16: =SUMIF(D5:D14,I16,F5:F14) -> 68000
I17: Февраль | J17: =SUMIF(D5:D14,I17,F5:F14) -> 28000
I18: Март | J18: =SUMIF(D5:D14,I18,F5:F14) -> 32000

Sheet Задание 6
A1: Задание 6. Стаж, надбавки и оплата труда
A4: № | B4: Место работы | C4: Дата поступления | D4: Дата увольнения (перевода) | E4: Должность | F4: Оклад | G4: Стаж, лет | H4: Надбавка | I4: Оплата труда | K4: Анализ
A5: 1 | B5: ООО Альфа | C5: 40918 | D5: 42875 | E5: Инженер | F5: 60000 | G5: =DATEDIF(C5,D5,"Y")+DATEDIF(C5,D5,"YM")/12 -> 5.3333333 | H5: =IF(G5<5,10%,IF(G5>10,20%,15%)) -> 0.15 | I5: =F5*(1+H5) -> 69000 | K5: Среднемесячная оплата за 2 последних года | L5: =AVERAGE(I9:I10) -> 94875
A6: 2 | B6: ООО Бета | C6: 42876 | D6: 44074 | E6: Менеджер | F6: 70000 | G6: =DATEDIF(C6,D6,"Y")+DATEDIF(C6,D6,"YM")/12 -> 3.25 | H6: =IF(G6<5,10%,IF(G6>10,20%,15%)) -> 0.1 | I6: =F6*(1+H6) -> 77000 | K6: Количество сотрудников с оплатой меньше средней | L6: =COUNTIF(I5:I10,"<"&AVERAGE(I5:I10)) -> 3
A7: 3 | B7: ООО Гамма | C7: 44075 | D7: 45291 | E7: Инженер | F7: 80000 | G7: =DATEDIF(C7,D7,"Y")+DATEDIF(C7,D7,"YM")/12 -> 3.25 | H7: =IF(G7<5,10%,IF(G7>10,20%,15%)) -> 0.1 | I7: =F7*(1+H7) -> 88000 | K7: Минимальная оплата | L7: =MIN(I5:I10) -> 69000
A8: 4 | B8: ООО Дельта | C8: 40210 | D8: 42400 | E8: Аналитик | F8: 65000 | G8: =DATEDIF(C8,D8,"Y")+DATEDIF(C8,D8,"YM")/12 -> 5.9166667 | H8: =IF(G8<5,10%,IF(G8>10,20%,15%)) -> 0.15 | I8: =F8*(1+H8) -> 74750 | K8: Максимальная оплата | L8: =MAX(I5:I10) -> 103500
A9: 5 | B9: ООО Эпсилон | C9: 42401 | D9: 44286 | E9: Менеджер | F9: 75000 | G9: =DATEDIF(C9,D9,"Y")+DATEDIF(C9,D9,"YM")/12 -> 5.0833333 | H9: =IF(G9<5,10%,IF(G9>10,20%,15%)) -> 0.15 | I9: =F9*(1+H9) -> 86250
A10: 6 | B10: ООО Зета | C10: 44287 | D10: 46295 | E10: Инженер | F10: 90000 | G10: =DATEDIF(C10,D10,"Y")+DATEDIF(C10,D10,"YM")/12 -> 5.4166667 | H10: =IF(G10<5,10%,IF(G10>10,20%,15%)) -> 0.15 | I10: =F10*(1+H10) -> 103500 | K10: Должность | L10: Средняя оплата
K11: Инженер | L11: =AVERAGEIF(E5:E10,K11,I5:I10) -> 86833.333
K12: Менеджер | L12: =AVERAGEIF(E5:E10,K12,I5:I10) -> 81625
K13: Аналитик | L13: =AVERAGEIF(E5:E10,K13,I5:I10) -> 74750

Sheet Задание 7
A1: Задание 7. Больничные листы
A4: ФИО | B4: Месяц | C4: Дата поступления | D4: Должность | E4: Рабочих дней в месяце | F4: Средний заработок | G4: Количество больничных дней | H4: Стаж | I4: К оплате по б/л | K4: Анализ
A5: Иванов | B5: Январь | C5: 45301 | D5: Инженер | E5: 22 | F5: 60000 | G5: 3 | H5: =DATEDIF(C5,TODAY(),"Y") -> 2 | I5: =F5*G5/E5*IF(H5<5,50%,IF(H5>8,100%,80%)) -> 4090.9091 | K5: Общая сумма оплаты больничных | L5: =SUM(I5:I16) -> 156177.27
A6: Петров | B6: Январь | C6: 42767 | D6: Менеджер | E6: 22 | F6: 61500 | G6: 5 | H6: =DATEDIF(C6,TODAY(),"Y") -> 9 | I6: =F6*G6/E6*IF(H6<5,50%,IF(H6>8,100%,80%)) -> 13977.273 | K6: Средний стаж | L6: =AVERAGE(H5:H16) -> 9.3333333
A7: Сидорова | B7: Январь | C7: 40238 | D7: Бухгалтер | E7: 22 | F7: 63000 | G7: 2 | H7: =DATEDIF(C7,TODAY(),"Y") -> 16 | I7: =F7*G7/E7*IF(H7<5,50%,IF(H7>8,100%,80%)) -> 5727.2727 | K7: Сотрудников со стажем меньше 8 лет | L7: =COUNTIF(H5:H16,"<8") -> 5
A8: Кузнецов | B8: Январь | C8: 44652 | D8: Дизайнер | E8: 22 | F8: 64500 | G8: 8 | H8: =DATEDIF(C8,TODAY(),"Y") -> 4 | I8: =F8*G8/E8*IF(H8<5,50%,IF(H8>8,100%,80%)) -> 11727.273 | K8: Минимум больничных дней | L8: =MIN(G5:G16) -> 1
A9: Иванов | B9: Февраль | C9: 42491 | D9: Инженер | E9: 22 | F9: 66000 | G9: 4 | H9: =DATEDIF(C9,TODAY(),"Y") -> 10 | I9: =F9*G9/E9*IF(H9<5,50%,IF(H9>8,100%,80%)) -> 12000 | K9: Максимум больничных дней | L9: =MAX(G5:G16) -> 10
A10: Петров | B10: Февраль | C10: 39600 | D10: Менеджер | E10: 22 | F10: 67500 | G10: 6 | H10: =DATEDIF(C10,TODAY(),"Y") -> 18 | I10: =F10*G10/E10*IF(H10<5,50%,IF(H10>8,100%,80%)) -> 18409.091
A11: Сидорова | B11: Февраль | C11: 45108 | D11: Бухгалтер | E11: 22 | F11: 69000 | G11: 1 | H11: =DATEDIF(C11,TODAY(),"Y") -> 3 | I11: =F11*G11/E11*IF(H11<5,50%,IF(H11>8,100%,80%)) -> 1568.1818 | K11: Месяц | L11: Среднее больничных дней | N11: Должность | O11: Больничных дней
A12: Кузнецов | B12: Февраль | C12: 42217 | D12: Дизайнер | E12: 22 | F12: 70500 | G12: 7 | H12: =DATEDIF(C12,TODAY(),"Y") -> 11 | I12: =F12*G12/E12*IF(H12<5,50%,IF(H12>8,100%,80%)) -> 22431.818 | K12: Январь | L12: =AVERAGEIF(B5:B16,K12,G5:G16) -> 4.5 | N12: Инженер | O12: =SUMIF(D5:D16,N12,G5:G16) -> 17
A13: Иванов | B13: Март | C13: 40057 | D13: Инженер | E13: 22 | F13: 72000 | G13: 10 | H13: =DATEDIF(C13,TODAY(),"Y") -> 17 | I13: =F13*G13/E13*IF(H13<5,50%,IF(H13>8,100%,80%)) -> 32727.273 | K13: Февраль | L13: =AVERAGEIF(B5:B16,K13,G5:G16) -> 4.5 | N13: Менеджер | O13: =SUMIF(D5:D16,N13,G5:G16) -> 13
A14: Петров | B14: Март | C14: 44470 | D14: Менеджер | E14: 22 | F14: 73500 | G14: 2 | H14: =DATEDIF(C14,TODAY(),"Y") -> 5 | I14: =F14*G14/E14*IF(H14<5,50%,IF(H14>8,100%,80%)) -> 5345.4545 | K14: Март | L14: =AVERAGEIF(B5:B16,K14,G5:G16) -> 5.25 | N14: Бухгалтер | O14: =SUMIF(D5:D16,N14,G5:G16) -> 8
A15: Сидорова | B15: Март | C15: 41944 | D15: Бухгалтер | E15: 22 | F15: 75000 | G15: 5 | H15: =DATEDIF(C15,TODAY(),"Y") -> 11 | I15: =F15*G15/E15*IF(H15<5,50%,IF(H15>8,100%,80%)) -> 17045.455 | N15: Дизайнер | O15: =SUMIF(D5:D16,N15,G5:G16) -> 19
A16: Кузнецов | B16: Март | C16: 43800 | D16: Дизайнер | E16: 22 | F16: 76500 | G16: 4 | H16: =DATEDIF(C16,TODAY(),"Y") -> 6 | I16: =F16*G16/E16*IF(H16<5,50%,IF(H16>8,100%,80%)) -> 11127.273

Sheet Задание 8
A1: Задание 8. Сотрудники: возраст, стаж и оплата
A4: ФИО | B4: Дата рождения | C4: Дата поступления | D4: Должность | E4: Оклад | F4: Возраст | G4: Стаж | H4: Надбавка | I4: Оплата труда | K4: Анализ
A5: Иванов | B5: 32874 | C5: 43110 | D5: Инженер | E5: 80000 | F5: =DATEDIF(B5,TODAY(),"Y") -> 36 | G5: =DATEDIF(C5,TODAY(),"Y") -> 8 | H5: =IF(G5<5,10%,IF(G5>10,20%,15%)) -> 0.15 | I5: =E5*(1+H5) -> 92000 | K5: Общая оплата труда | L5: =SUM(I5:I14) -> 980850
A6: Петров | B6: 31080 | C6: 40941 | D6: Менеджер | E6: 90000 | F6: =DATEDIF(B6,TODAY(),"Y") -> 41 | G6: =DATEDIF(C6,TODAY(),"Y") -> 14 | H6: =IF(G6<5,10%,IF(G6>10,20%,15%)) -> 0.2 | I6: =E6*(1+H6) -> 108000 | K6: Средняя оплата | L6: =AVERAGE(I5:I14) -> 98085
A7: Сидорова | B7: 34761 | C7: 43893 | D7: Бухгалтер | E7: 70000 | F7: =DATEDIF(B7,TODAY(),"Y") -> 31 | G7: =DATEDIF(C7,TODAY(),"Y") -> 6 | H7: =IF(G7<5,10%,IF(G7>10,20%,15%)) -> 0.15 | I7: =E7*(1+H7) -> 80500 | K7: Количество с оплатой меньше средней | L7: =COUNTIF(I5:I14,"<"&L6) -> 6
A8: Кузнецов | B8: 28584 | C8: 39542 | D8: Инженер | E8: 95000 | F8: =DATEDIF(B8,TODAY(),"Y") -> 48 | G8: =DATEDIF(C8,TODAY(),"Y") -> 18 | H8: =IF(G8<5,10%,IF(G8>10,20%,15%)) -> 0.2 | I8: =E8*(1+H8) -> 114000 | K8: Минимальная оплата | L8: =MIN(I5:I14) -> 80500
A9: Иванов | B9: 33729 | C9: 42495 | D9: Менеджер | E9: 85000 | F9: =DATEDIF(B9,TODAY(),"Y") -> 34 | G9: =DATEDIF(C9,TODAY(),"Y") -> 10 | H9: =IF(G9<5,10%,IF(G9>10,20%,15%)) -> 0.15 | I9: =E9*(1+H9) -> 97750 | K9: Максимальная оплата | L9: =MAX(I5:I14) -> 120000
A10: Петров | B10: 29378 | C10: 40335 | D10: Бухгалтер | E10: 75000 | F10: =DATEDIF(B10,TODAY(),"Y") -> 46 | G10: =DATEDIF(C10,TODAY(),"Y") -> 16 | H10: =IF(G10<5,10%,IF(G10>10,20%,15%)) -> 0.2 | I10: =E10*(1+H10) -> 90000
A11: Сидорова | B11: 35983 | C11: 44749 | D11: Инженер | E11: 82000 | F11: =DATEDIF(B11,TODAY(),"Y") -> 28 | G11: =DATEDIF(C11,TODAY(),"Y") -> 4 | H11: =IF(G11<5,10%,IF(G11>10,20%,15%)) -> 0.1 | I11: =E11*(1+H11) -> 90200 | K11: Должность | L11: Средняя оплата
A12: Кузнецов | B12: 31997 | C12: 41859 | D12: Менеджер | E12: 88000 | F12: =DATEDIF(B12,TODAY(),"Y") -> 39 | G12: =DATEDIF(C12,TODAY(),"Y") -> 12 | H12: =IF(G12<5,10%,IF(G12>10,20%,15%)) -> 0.2 | I12: =E12*(1+H12) -> 105600 | K12: Инженер | L12: =AVERAGEIF(D5:D14,K12,I5:I14) -> 104050
A13: Иванов | B13: 34221 | C13: 43717 | D13: Бухгалтер | E13: 72000 | F13: =DATEDIF(B13,TODAY(),"Y") -> 33 | G13: =DATEDIF(C13,TODAY(),"Y") -> 7 | H13: =IF(G13<5,10%,IF(G13>10,20%,15%)) -> 0.15 | I13: =E13*(1+H13) -> 82800 | K13: Менеджер | L13: =AVERAGEIF(D5:D14,K13,I5:I14) -> 103783.33
A14: Петров | B14: 30234 | C14: 40826 | D14: Инженер | E14: 100000 | F14: =DATEDIF(B14,TODAY(),"Y") -> 43 | G14: =DATEDIF(C14,TODAY(),"Y") -> 14 | H14: =IF(G14<5,10%,IF(G14>10,20%,15%)) -> 0.2 | I14: =E14*(1+H14) -> 120000 | K14: Бухгалтер | L14: =AVERAGEIF(D5:D14,K14,I5:I14) -> 84433.333

Sheet Задание 9
A1: Задание 9. Больничные: даты, стаж, дни и оплата
A4: ФИО | B4: Месяц | C4: Дата поступления | D4: Рабочих дней в месяце | E4: Средний заработок | F4: Дата выдачи больничного | G4: Дата окончания больничного | H4: Стаж | I4: Дней по больничному листу | J4: К оплате по больничному | L4: Анализ | P4: Количество больничных дней для каждого сотрудника
A5: Иванов | B5: Январь | C5: 45292 | D5: 22 | E5: 60000 | F5: 46027 | G5: 46029 | H5: =DATEDIF(C5,TODAY(),"Y") -> 2 | I5: =G5-F5+1 -> 3 | J5: =E5*I5/D5*IF(H5<5,50%,IF(H5>8,100%,80%)) -> 4090.9091 | L5: Общая сумма оплаты больничных | M5: =SUM(J5:J14) -> 176036.36 | P5: ФИО | Q5: Дни
A6: Петров | B6: Январь | C6: 44594 | D6: 22 | E6: 62000 | F6: 46059 | G6: 46064 | H6: =DATEDIF(C6,TODAY(),"Y") -> 4 | I6: =G6-F6+1 -> 6 | J6: =E6*I6/D6*IF(H6<5,50%,IF(H6>8,100%,80%)) -> 8454.5455 | L6: Средний стаж | M6: =AVERAGE(H5:H14) -> 10.9 | P6: =A5 -> Иванов | Q6: =I5 -> 3
A7: Сидорова | B7: Январь | C7: 43893 | D7: 22 | E7: 64000 | F7: 46088 | G7: 46095 | H7: =DATEDIF(C7,TODAY(),"Y") -> 6 | I7: =G7-F7+1 -> 8 | J7: =E7*I7/D7*IF(H7<5,50%,IF(H7>8,100%,80%)) -> 18618.182 | L7: Количество сотрудников со стажем > 8 лет | M7: =COUNTIF(H5:H14,">8") -> 6 | P7: =A6 -> Петров | Q7: =I6 -> 6
A8: Кузнецов | B8: Январь | C8: 43194 | D8: 22 | E8: 66000 | F8: 46030 | G8: 46033 | H8: =DATEDIF(C8,TODAY(),"Y") -> 8 | I8: =G8-F8+1 -> 4 | J8: =E8*I8/D8*IF(H8<5,50%,IF(H8>8,100%,80%)) -> 9600 | L8: Минимальный средний заработок | M8: =MIN(E5:E14) -> 60000 | P8: =A7 -> Сидорова | Q8: =I7 -> 8
A9: Иванов | B9: Февраль | C9: 42495 | D9: 22 | E9: 68000 | F9: 46062 | G9: 46072 | H9: =DATEDIF(C9,TODAY(),"Y") -> 10 | I9: =G9-F9+1 -> 11 | J9: =E9*I9/D9*IF(H9<5,50%,IF(H9>8,100%,80%)) -> 34000 | L9: Максимальный средний заработок | M9: =MAX(E5:E14) -> 78000 | P9: =A8 -> Кузнецов | Q9: =I8 -> 4
A10: Петров | B10: Февраль | C10: 41796 | D10: 22 | E10: 70000 | F10: 46091 | G10: 46095 | H10: =DATEDIF(C10,TODAY(),"Y") -> 12 | I10: =G10-F10+1 -> 5 | J10: =E10*I10/D10*IF(H10<5,50%,IF(H10>8,100%,80%)) -> 15909.091 | P10: =A9 -> Иванов | Q10: =I9 -> 11
A11: Сидорова | B11: Февраль | C11: 41097 | D11: 22 | E11: 72000 | F11: 46033 | G11: 46039 | H11: =DATEDIF(C11,TODAY(),"Y") -> 14 | I11: =G11-F11+1 -> 7 | J11: =E11*I11/D11*IF(H11<5,50%,IF(H11>8,100%,80%)) -> 22909.091 | L11: Месяц | M11: К оплате по больничному | N11: Количество дней по больничному | P11: =A10 -> Петров | Q11: =I10 -> 5
A12: Кузнецов | B12: Февраль | C12: 40398 | D12: 22 | E12: 74000 | F12: 46065 | G12: 46067 | H12: =DATEDIF(C12,TODAY(),"Y") -> 16 | I12: =G12-F12+1 -> 3 | J12: =E12*I12/D12*IF(H12<5,50%,IF(H12>8,100%,80%)) -> 10090.909 | L12: Январь | M12: =SUMIF(B5:B14,L12,J5:J14) -> 40763.636 | N12: =SUMIF(B5:B14,L12,I5:I14) -> 21 | P12: =A11 -> Сидорова | Q12: =I11 -> 7
A13: Иванов | B13: Март | C13: 39700 | D13: 22 | E13: 76000 | F13: 46094 | G13: 46102 | H13: =DATEDIF(C13,TODAY(),"Y") -> 18 | I13: =G13-F13+1 -> 9 | J13: =E13*I13/D13*IF(H13<5,50%,IF(H13>8,100%,80%)) -> 31090.909 | L13: Февраль | M13: =SUMIF(B5:B14,L13,J5:J14) -> 82909.091 | N13: =SUMIF(B5:B14,L13,I5:I14) -> 26 | P13: =A12 -> Кузнецов | Q13: =I12 -> 3
A14: Петров | B14: Март | C14: 39000 | D14: 22 | E14: 78000 | F14: 46036 | G14: 46041 | H14: =DATEDIF(C14,TODAY(),"Y") -> 19 | I14: =G14-F14+1 -> 6 | J14: =E14*I14/D14*IF(H14<5,50%,IF(H14>8,100%,80%)) -> 21272.727 | L14: Март | M14: =SUMIF(B5:B14,L14,J5:J14) -> 52363.636 | N14: =SUMIF(B5:B14,L14,I5:I14) -> 15 | P14: =A13 -> Иванов | Q14: =I13 -> 9
P15: =A14 -> Петров | Q15: =I14 -> 6

Sheet Задание 10
A1: Задание 10. Графики функций
A3: X | B3: SIN(X) | C3: COS(X) | D3: Парабола X^2 | E3: Z
A4: -3 | B4: =SIN(A4) -> -0.14112001 | C4: =COS(A4) -> -0.9899925 | D4: =A4^2 -> 9 | E4: =IF(A4>=0,5*A4,A4^2) -> 9
A5: -2.8 | B5: =SIN(A5) -> -0.33498815 | C5: =COS(A5) -> -0.94222234 | D5: =A5^2 -> 7.84 | E5: =IF(A5>=0,5*A5,A5^2) -> 7.84
A6: -2.6 | B6: =SIN(A6) -> -0.51550137 | C6: =COS(A6) -> -0.85688875 | D6: =A6^2 -> 6.76 | E6: =IF(A6>=0,5*A6,A6^2) -> 6.76
A7: -2.4 | B7: =SIN(A7) -> -0.67546318 | C7: =COS(A7) -> -0.73739372 | D7: =A7^2 -> 5.76 | E7: =IF(A7>=0,5*A7,A7^2) -> 5.76
A8: -2.2 | B8: =SIN(A8) -> -0.8084964 | C8: =COS(A8) -> -0.58850112 | D8: =A8^2 -> 4.84 | E8: =IF(A8>=0,5*A8,A8^2) -> 4.84
A9: -2 | B9: =SIN(A9) -> -0.90929743 | C9: =COS(A9) -> -0.41614684 | D9: =A9^2 -> 4 | E9: =IF(A9>=0,5*A9,A9^2) -> 4
A10: -1.8 | B10: =SIN(A10) -> -0.97384763 | C10: =COS(A10) -> -0.22720209 | D10: =A10^2 -> 3.24 | E10: =IF(A10>=0,5*A10,A10^2) -> 3.24
A11: -1.6 | B11: =SIN(A11) -> -0.9995736 | C11: =COS(A11) -> -0.029199522 | D11: =A11^2 -> 2.56 | E11: =IF(A11>=0,5*A11,A11^2) -> 2.56
A12: -1.4 | B12: =SIN(A12) -> -0.98544973 | C12: =COS(A12) -> 0.16996714 | D12: =A12^2 -> 1.96 | E12: =IF(A12>=0,5*A12,A12^2) -> 1.96
A13: -1.2 | B13: =SIN(A13) -> -0.93203909 | C13: =COS(A13) -> 0.36235775 | D13: =A13^2 -> 1.44 | E13: =IF(A13>=0,5*A13,A13^2) -> 1.44
A14: -1 | B14: =SIN(A14) -> -0.84147098 | C14: =COS(A14) -> 0.54030231 | D14: =A14^2 -> 1 | E14: =IF(A14>=0,5*A14,A14^2) -> 1
A15: -0.8 | B15: =SIN(A15) -> -0.71735609 | C15: =COS(A15) -> 0.69670671 | D15: =A15^2 -> 0.64 | E15: =IF(A15>=0,5*A15,A15^2) -> 0.64
... A34: 3 | B34: =SIN(A34) -> 0.14112001 | C34: =COS(A34) -> -0.9899925 | D34: =A34^2 -> 9 | E34: =IF(A34>=0,5*A34,A34^2) -> 15
